xarray_leaflet/__init__.py
xarray_leaflet/transform.py
xarray_leaflet/utils.py
xarray_leaflet/xarray_leaflet.py
xarray_leaflet-0.2.3.dist-info/METADATA
xarray_leaflet-0.2.3.dist-info/WHEEL
xarray_leaflet-0.2.3.dist-info/licenses/LICENSE
xarray_leaflet-0.2.3.dist-info/RECORD
