Metadata-Version: 2.1
Name: xarray_leaflet
Version: 0.2.3
Summary: An xarray extension for map plotting
Project-URL: Homepage, https://github.com/xarray-contrib/xarray_leaflet
Author-email: David Brochart <david.brochart@gmail.com>
License: MIT License
License-File: LICENSE
Keywords: jupyter,leaflet,server,xarray
Requires-Python: >=3.5
Requires-Dist: affine>=2
Requires-Dist: ipyleaflet>=0.13.1
Requires-Dist: ipyspin>=0.1.1
Requires-Dist: ipyurl>=0.1.2
Requires-Dist: jupyter-server-xarray-leaflet>=0.2.3
Requires-Dist: matplotlib>=3
Requires-Dist: mercantile>=1
Requires-Dist: pillow>=7
Requires-Dist: rioxarray>=0.0.30
